setup.py
uploaderjs/__init__.py
uploaderjs.egg-info/PKG-INFO
uploaderjs.egg-info/SOURCES.txt
uploaderjs.egg-info/dependency_links.txt
uploaderjs.egg-info/not-zip-safe
uploaderjs.egg-info/requires.txt
uploaderjs.egg-info/top_level.txt