Metadata-Version: 1.0
Name: uploaderjs
Version: 1.0
Summary: Official from uploaderjs
Home-page: https://uploaderjs@bitbucket.org/uploaderjs/uploaderjs_pkpy.git
Author: Jure Bernava Prah
Author-email: webjure@gmail.com
License: MIT
Platform: UNKNOWN
